gitolog/__init__.py
gitolog/__main__.py
gitolog/build.py
gitolog/cli.py
gitolog/providers.py
gitolog/style.py
gitolog/templates/__init__.py
gitolog/templates/angular/changelog.md
gitolog/templates/angular/commit.md
gitolog/templates/angular/section.md
gitolog/templates/angular/version.md
gitolog/templates/keepachangelog/changelog.md
gitolog/templates/keepachangelog/commit.md
gitolog/templates/keepachangelog/section.md
gitolog/templates/keepachangelog/version.md
gitolog-0.1.1.dist-info/METADATA
gitolog-0.1.1.dist-info/RECORD
gitolog-0.1.1.dist-info/WHEEL
gitolog-0.1.1.dist-info/entry_points.txt
gitolog-0.1.1.dist-info/top_level.txt
