Metadata-Version: 2.1
Name: gitolog
Version: 0.1.1
Summary: Automatic Changelog generator using Jinja2 templates.
Home-page: https://gitlab.com/pawamoy/gitolog
Author: Timothée Mazzucotelli
Author-email: timothee.mazzucotelli@protonmail.com
License: ISC
Keywords: automatic,changelog,generator,automatic-changelog-generator,keep-a-changelog,git,git-logs
Platform: UNKNOWN
Classifier: Development Status :: 3 - Alpha
Classifier: Intended Audience :: Developers
Classifier: License :: OSI Approved :: ISC License (ISCL)
Classifier: Programming Language :: Python
Classifier: Programming Language :: Python :: 3
Classifier: Topic :: Software Development
Requires-Dist: jinja2
